LICENSE
MANIFEST.in
README.md
setup.cfg
setup.py
golos/__init__.py
golos/account.py
golos/aes.py
golos/amount.py
golos/block.py
golos/blockchain.py
golos/blog.py
golos/cli.py
golos/commit.py
golos/converter.py
golos/dex.py
golos/instance.py
golos/post.py
golos/profile.py
golos/steem.py
golos/steemd.py
golos/transactionbuilder.py
golos/utils.py
golos/wallet.py
golos/witness.py
golosbase/__init__.py
golosbase/account.py
golosbase/base58.py
golosbase/base_client.py
golosbase/bip38.py
golosbase/chains.py
golosbase/connector.py
golosbase/dictionary.py
golosbase/exceptions.py
golosbase/http_client.py
golosbase/memo.py
golosbase/operationids.py
golosbase/operations.py
golosbase/storage.py
golosbase/transactions.py
golosbase/types.py
golosbase/ws_client.py
steep_golos.egg-info/PKG-INFO
steep_golos.egg-info/SOURCES.txt
steep_golos.egg-info/dependency_links.txt
steep_golos.egg-info/entry_points.txt
steep_golos.egg-info/requires.txt
steep_golos.egg-info/top_level.txt