Metadata-Version: 1.0
Name: steep-golos
Version: 0.0.20
Summary: Fork of official python STEEM library for Golos blockchain
Home-page: https://github.com/Chainers/steep-golos
Author: @steepshot
Author-email: steepshot.org@gmail.com
License: The MIT License (MIT)
